environ_maiden
