Metadata-Version: 1.0
Name: environ-maiden
Version: 0.1.3
Summary: Simplifies converting ENV variables to config values.
Home-page: http://github.com/seanbrant/environ-maiden
Author: Sean Brant
Author-email: brant.sean@gmail.com
License: BSD
Platform: UNKNOWN
Classifier: Development Status :: 4 - Beta
Classifier: Intended Audience :: Developers
Classifier: License :: OSI Approved :: BSD License
Classifier: Operating System :: OS Independent
Classifier: Programming Language :: Python
Classifier: Programming Language :: Python :: 2.5
Classifier: Programming Language :: Python :: 2.6
Classifier: Programming Language :: Python :: 2.7
Classifier: Topic :: Utilities
